PyPFD/PyPFDAvgDevices.py
PyPFD/PyPFDClass.py
PyPFD/PyPFDDevices.py
PyPFD/PyPFDMarkov.py
PyPFD/PyPFDMarkovTransition.py
PyPFD/PyPFDRBDAvg.py
PyPFD/__init__.py
pypfd-2025.0.0.9.dist-info/licenses/LICENSE
pypfd-2025.0.0.9.dist-info/METADATA
pypfd-2025.0.0.9.dist-info/WHEEL
pypfd-2025.0.0.9.dist-info/top_level.txt
pypfd-2025.0.0.9.dist-info/RECORD
