Metadata-Version: 2.4
Name: PyPFD
Version: 2025.0.0.9
Summary: PFDavg calculation
Author-email: Rafael Rocha <rafa.rocha@gmail.com>
Keywords: SIS,SIF,IEC61508,IEC61511,PFD,reliability,functional safety,1oo1,1oo2,2oo3,2oo2,1oo3
Classifier: Programming Language :: Python :: 3
Classifier: Operating System :: OS Independent
Requires-Python: >=3.8
License-File: LICENSE
Dynamic: license-file
